README.rst
setup.py
sas32kd/__init__.py
sas32kd.egg-info/PKG-INFO
sas32kd.egg-info/SOURCES.txt
sas32kd.egg-info/dependency_links.txt
sas32kd.egg-info/not-zip-safe
sas32kd.egg-info/top_level.txt