Metadata-Version: 1.0
Name: sas32kd
Version: 0.0.2
Summary: SAS 32KD USI Protocol Library
Home-page: UNKNOWN
Author: avc
Author-email: avcsec@protonmail.com
License: MIT
Platform: UNKNOWN
